MANIFEST.in
README.rst
setup.py
bin/delgado
delgado/__init__.py
delgado/decorators.py
delgado/exceptions.py
delgado/loader.py
delgado/logger.py
delgado/main.py
delgado/server.py
delgado/util.py
delgado.egg-info/PKG-INFO
delgado.egg-info/SOURCES.txt
delgado.egg-info/dependency_links.txt
delgado.egg-info/entry_points.txt
delgado.egg-info/not-zip-safe
delgado.egg-info/requires.txt
delgado.egg-info/top_level.txt
delgado/services/__init__.py
delgado/services/pytest.py
delgado/tests/test_loader.py
delgado/tests/test_main.py
delgado/tests/test_server.py
delgado/tests/__pycache__/test_loader.cpython-26-PYTEST.pyc
delgado/tests/__pycache__/test_loader.cpython-27-PYTEST.pyc
delgado/tests/__pycache__/test_loader.cpython-33-PYTEST.pyc
delgado/tests/__pycache__/test_main.cpython-26-PYTEST.pyc
delgado/tests/__pycache__/test_main.cpython-27-PYTEST.pyc
delgado/tests/__pycache__/test_main.cpython-33-PYTEST.pyc
delgado/tests/__pycache__/test_server.cpython-26-PYTEST.pyc
delgado/tests/__pycache__/test_server.cpython-27-PYTEST.pyc
delgado/tests/__pycache__/test_server.cpython-33-PYTEST.pyc