Metadata-Version: 1.0
Name: delgado
Version: 0.0.1
Summary: Command executor over UDS
Home-page: http://github.com/alfredodeza/delgado
Author: Alfredo Deza
Author-email: alfredodeza [at] gmail.com
License: MIT
Keywords: commands,unix,socket,execute,terminal
Platform: UNKNOWN
Classifier: Development Status :: 4 - Beta
Classifier: Intended Audience :: Developers
Classifier: License :: OSI Approved :: MIT License
Classifier: Topic :: Software Development :: Build Tools
Classifier: Topic :: Utilities
Classifier: Operating System :: MacOS :: MacOS X
Classifier: Operating System :: POSIX
Classifier: Programming Language :: Python :: 2.6
Classifier: Programming Language :: Python :: 2.7
Classifier: Programming Language :: Python :: 3.3
